batch.py
asstosrt/__init__.py
asstosrt/translate.py
asstosrt-0.1.6.data/data/README.rst
asstosrt-0.1.6.dist-info/DESCRIPTION.rst
asstosrt-0.1.6.dist-info/METADATA
asstosrt-0.1.6.dist-info/RECORD
asstosrt-0.1.6.dist-info/WHEEL
asstosrt-0.1.6.dist-info/entry_points.txt
asstosrt-0.1.6.dist-info/metadata.json
asstosrt-0.1.6.dist-info/top_level.txt
