Metadata-Version: 1.1
Name: asstosrt
Version: 0.1.6
Summary: A tool that convert ASS/SSA subtitle to SRT format
Home-page: https://github.com/sorz/asstosrt/
Author: XiErCh
Author-email: orz@sorz.org
License: UNKNOWN
Platform: UNKNOWN
Classifier: Development Status :: 4 - Beta
Classifier: Environment :: Console
Classifier: License :: OSI Approved :: MIT License
Classifier: Programming Language :: Python :: 2
Classifier: Programming Language :: Python :: 2.7
Classifier: Programming Language :: Python :: 3
Classifier: Topic :: Text Processing
